LICENSE
MANIFEST.in
README.md
requirements.txt
setup.py
cbhist/__init__.py
cbhist/candles.py
cbhist/historical.py
cbhist.egg-info/PKG-INFO
cbhist.egg-info/SOURCES.txt
cbhist.egg-info/dependency_links.txt
cbhist.egg-info/not-zip-safe
cbhist.egg-info/requires.txt
cbhist.egg-info/top_level.txt