Metadata-Version: 2.1
Name: cbhist
Version: 0.0.4
Summary: A python library for pulling in historical candles from coinbase.
Home-page: https://github.com/8W9aG/cbhist
Author: Will Sackfield
Author-email: will.sackfield@gmail.com
License: MIT
Keywords: coinbase history historical price candle
Classifier: License :: OSI Approved :: MIT License
Classifier: Programming Language :: Python :: 3
License-File: LICENSE
Requires-Dist: requests>=2.31.0
Requires-Dist: pandas>=2.0.3
Requires-Dist: tenacity>=8.3.0
